Workbook

Sheet Inputs
A1: MODEL INPUTS — All Assumptions Centralized
A3: Product Data (from PayMe assignment)
A4: Product | B4: ARPU (ILS) | C4: Activation Rate | D4: Sales Cycle (weeks)
A5: Payments | B5: 100 | C5: 0.15 | D5: 4
A6: Accounting | B6: 150 | C6: 0.25 | D6: 2
A7: Marketing (Promoter) | B7: 1500 | C7: 0.25 | D7: 4
A9: Partner Assumptions
A10: # | B10: Partner | C10: Type | D10: Ecosystem | E10: Exposure % (Cons.) | F10: Exposure % (Upside) | G10: Activation % | H10: Blended ARPU | I10: Source
A11: 1 | B11: 10bis | C11: Outbound | D11: 6000 | E11: 0.15 | F11: 0.3 | G11: 0.25 | H11: 150 | I11: Calcalist 2025; Wolt PoC
A12: 2 | B12: Plannie | C12: Outbound | D12: 3000 | E12: 0.1 | F12: 0.2 | G12: 0.2 | H12: 200 | I12: Market research; no payments = fit
A13: 3 | B13: Arbox | C13: Outbound | D13: 7000 | E13: 0.05 | F13: 0.1 | G13: 0.25 | H13: 250 | I13: Arbox website; Capterra
A14: 4 | B14: Assuta Pilot | C14: Outbound | D14: 400 | E14: 0.05 | F14: 0.125 | G14: 0.25 | H14: 250 | I14: Assuta website
A15: 5 | B15: Yango Deli | C15: Outbound | D15: 2000 | E15: 0.1 | F15: 0.2 | G15: 0.25 | H15: 150 | I15: Yandex subsidiary research
A16: 6 | B16: Wolt expand (existing) | C16: Inbound | D16: 10000 | E16: 0.1 | F16: 0.15 | G16: 0.25 | H16: 150 | I16: PayMe case study; Wikipedia
A17: 7 | B17: Wolt Merchants | C17: Inbound | D17: 4000 | E17: 0.05 | F17: 0.1 | G17: 0.25 | H17: 150 | I17: Wolt: 70K merchants global
A18: 8 | B18: Wix Upsell | C18: Inbound | D18: 20000 | E18: 0.03 | F18: 0.05 | G18: 0.25 | H18: 150 | I18: Wix: millions global; IL ~20K
A19: 9 | B19: Isracard/Cal | C19: Inbound | D19: 50000 | E19: 0 | F19: 0.01 | G19: 0.2 | H19: 175 | I19: Major IL issuer
A22: Monthly Ramp Schedule (% of M4 exposed base onboarded)
A23: # | B23: Partner | C23: M1 Ramp | D23: M2 Ramp | E23: M3 Ramp | F23: M4 Ramp | G23: M1 Ramp (Up) | H23: M2 Ramp (Up) | I23: M3 Ramp (Up) | J23: M4 Ramp (Up)
A24: 1 | B24: 10bis | C24: 0 | D24: 0.100741 | E24: 0.500741 | F24: 1 | G24: 0 | H24: 0.074074 | I24: 0.296296 | J24: 0.592593
A25: 2 | B25: Plannie | C25: 0 | D25: 0.1 | E25: 0.4 | F25: 1 | G25: 0 | H25: 0.1 | I25: 0.3 | J25: 0.75
A26: 3 | B26: Arbox | C26: 0 | D26: 0 | E26: 0.201143 | F26: 0.804571 | G26: 0 | H26: 0 | I26: 0.171429 | J26: 0.571429
A27: 4 | B27: Assuta Pilot | C27: 0 | D27: 0 | E27: 0.5 | F27: 1 | G27: 0 | H27: 0 | I27: 0.48 | J27: 0.96
A28: 5 | B28: Yango Deli | C28: 0 | D28: 0 | E28: 0.3 | F28: 1 | G28: 0 | H28: 0 | I28: 0.2 | J28: 0.666667
A29: 6 | B29: Wolt expand (existing) | C29: 0.133333 | D29: 0.2 | E29: 0.3 | F29: 0.4 | G29: 0.106667 | H29: 0.16 | I29: 0.248889 | J29: 0.32
A30: 7 | B30: Wolt Merchants | C30: 0 | D30: 0 | E30: 0.3 | F30: 1 | G30: 0 | H30: 0 | I30: 0.233333 | J30: 0.666667
A31: 8 | B31: Wix Upsell | C31: 0 | D31: 0.066667 | E31: 0.2 | F31: 0.333333 | G31: 0 | H31: 0.053333 | I31: 0.16 | J31: 0.32
A32: 9 | B32: Isracard/Cal | C32: 0 | D32: 0 | E32: 0 | F32: 0 | G32: 0 | H32: 0 | I32: 0 | J32: 0.285714

Sheet Partner Selection
A1: TABLE: Partner Selection
A3: Partner | B3: Relevant Products | C3: Est. Sellers / Businesses | D3: Why Selected
A4: 10bis (Outbound) | B4: Accounting (primary), Payments (secondary) | C4: ~5,000-8,000 freelance couriers | D4: Switched to 100% freelancers in 2025. Currently uses Keycost (99 ILS/mo). Wolt PoC proven. Quick Win.
A5: Yango Deli (Outbound) | B5: Accounting | C5: ~1,000-3,000 couriers | D5: Yandex subsidiary. Same Wolt model. Growing in Gush Dan.
A6: Arbox (Outbound) | B6: Accounting + Promoter (add-on) | C6: 5,000-10,000 businesses | D6: #1 Israeli management platform for fitness/beauty/clinics. Has payments, missing bookkeeping. Huge volume.
A7: Plannie (Outbound) | B7: Payments + Accounting | C7: ~2,000-5,000 businesses | D7: Israeli scheduling platform. Weak on payments. PayMe = natural fit. Short sales cycle.
A8: Assuta (Outbound) | B8: Accounting + Payments | C8: ~300-500 independent physicians | D8: Largest private hospital network. One deal = hundreds of doctors. Major credibility.
A9: Herzliya Medical Center (Outbound) | B9: Accounting + Payments | C9: ~500 specialist physicians | D9: Premium private hospital. Quality signal for all other segments.
A10: Wolt Merchants (Inbound) | B10: Accounting + Promoter | C10: ~3,000-5,000 merchant partners | D10: Already serves couriers. Merchants get zero financial services. Upsell on existing relationship.
A11: Wix Upsell (Inbound) | B11: Accounting + Promoter | C11: ~10,000-30,000 IL merchants | D11: Already on PayMe Payments. Wix Payments unavailable in Israel. Missing local invoicing.
A12: Isracard/Cal (Inbound) | B12: Accounting + Promoter (bundle) | C12: ~50,000+ SMBs | D12: Already distributes PayMe Payments as White Label. Bundle differentiates from competitors.
A13: Zester (Inbound) | B13: Accounting | C13: ~500-1,000 restaurants | D13: Already uses PayMe for B2B supplier payments. Adding Accounting = complete suite.

Sheet Weekly Activity (Wk 1-12)
A1: TABLE: Weekly Activity & Partner Progress (Weeks 1-12)
C3: Month 1 | G3: Month 2 | K3: Month 3
A4: Partner | B4: Product | C4: Week 1 | D4: Week 2 | E4: Week 3 | F4: Week 4 | G4: Week 5 | H4: Week 6 | I4: Week 7 | J4: Week 8 | K4: Week 9 | L4: Week 10 | M4: Week 11 | N4: Week 12
A5: 10bis | B5: Accounting | C5: Research decision makers | D5: Outreach (LinkedIn+email) | E5: Meeting: Wolt case study | F5: Follow-up + proposal | G5: Negotiate terms | H5: Sign partnership | I5: Integration kickoff | J5: Pilot: 100 couriers | K5: Expand to 500 | L5: Full rollout | M5: Optimize activation | N5: Measure MRR; scale
A6: Plannie | B6: Payments+Accounting | C6: Research product gaps | D6: Initial outreach | E6: Meeting: P+A bundle | F6: Proposal + demo | G6: Sign | H6: Integration | I6: Soft launch: 50 businesses | J6: Expand to 200 | K6: Full rollout | L6: Optimize onboarding | M6: Add Promoter upsell | N6: Measure; scale
A7: Arbox | B7: Accounting+Promoter | C7: Deep-dive Arbox ecosystem | D7: ID decision makers | E7: Outreach + one-pager | F7: Meeting: Accounting add-on | G7: Technical feasibility | H7: Negotiate terms | I7: Sign LOI | J7: Integration dev | K7: Beta: 100 businesses | L7: Expand to 500 | M7: Full rollout | N7: Add Promoter
A8: Assuta Pilot | B8: Accounting+Payments | C8: Map physician groups | D8: Outreach to 2-3 groups | E8: Meeting: first group | F8: Pilot proposal | G8: Sign pilot | H8: Onboard 10-20 doctors | I8: Measure results | J8: Present to management | K8: Expand: 2nd group | L8: 3rd group | M8: Approach HMC w/ case study | N8: Ongoing expansion
A9: Wolt Merchants (Inbound) | B9: Accounting+Promoter | C9: Analyze merchant data | D9: Internal mtg: Wolt ops | E9: Propose Accounting | F9: Align rollout plan | G9: Pilot: 50 restaurants | H9: Expand to 200 | I9: Measure activation | J9: Optimize onboarding | K9: Full rollout | L9: Add Promoter | M9: Scale Promoter | N9: Measure combined MRR
A10: Wix Upsell (Inbound) | B10: Accounting+Promoter | C10: Analyze IL merchant base | D10: Internal mtg: Wix fintech | E10: Propose Accounting bundle | F10: Define scope | G10: Technical planning | H10: Dev kickoff | I10: Beta: 100 merchants | J10: Expand beta | K10: Soft launch | L10: Full rollout | M10: Add Promoter | N10: Scale + optimize
A11: Isracard/Cal (Inbound) | B11: Accounting+Promoter | C11: Map merchant base | D11: Internal meeting | E11: Present A+P bundle | F11: Build business case | G11: Negotiate | H11: Sign expansion | I11: Integration planning | J11: Beta launch | K11: Expand | L11: Full rollout | M11: Promoter launch | N11: Scale

Sheet Conservative (100K)
A1: TABLE: Monthly Revenue Forecast — Conservative (Floor)
A2: All MRR cells = Inputs!Ecosystem x Exposure x Ramp x Activation x ARPU. Change any input and the model recalculates.
A4: Partner | B4: Product | C4: Ecosystem | D4: Exposed (M4) | E4: Activation | F4: Active (M4) | G4: ARPU | H4: Month 1 | I4: Month 2 | J4: Month 3 | K4: Month 4
A5: =Inputs!B11 -> 10bis | B5: Accounting | C5: =Inputs!D11 -> 6000 | D5: =Inputs!D11*Inputs!E11 -> 900 | E5: =Inputs!G11 -> 0.25 | F5: =D5*E5 -> 225 | G5: =Inputs!H11 -> 150 | H5: =ROUND(Inputs!D11*Inputs!E11*Inputs!C24*Inputs!G11*Inputs!H11,0) -> 0 | I5: =ROUND(Inputs!D11*Inputs!E11*Inputs!D24*Inputs!G11*Inputs!H11,0) -> 3400 | J5: =ROUND(Inputs!D11*Inputs!E11*Inputs!E24*Inputs!G11*Inputs!H11,0) -> 16900 | K5: =ROUND(Inputs!D11*Inputs!E11*Inputs!F24*Inputs!G11*Inputs!H11,0) -> 33750
A6: =Inputs!B12 -> Plannie | B6: Payments+Accounting | C6: =Inputs!D12 -> 3000 | D6: =Inputs!D12*Inputs!E12 -> 300 | E6: =Inputs!G12 -> 0.2 | F6: =D6*E6 -> 60 | G6: =Inputs!H12 -> 200 | H6: =ROUND(Inputs!D12*Inputs!E12*Inputs!C25*Inputs!G12*Inputs!H12,0) -> 0 | I6: =ROUND(Inputs!D12*Inputs!E12*Inputs!D25*Inputs!G12*Inputs!H12,0) -> 1200 | J6: =ROUND(Inputs!D12*Inputs!E12*Inputs!E25*Inputs!G12*Inputs!H12,0) -> 4800 | K6: =ROUND(Inputs!D12*Inputs!E12*Inputs!F25*Inputs!G12*Inputs!H12,0) -> 12000
A7: =Inputs!B13 -> Arbox | B7: Accounting+Promoter | C7: =Inputs!D13 -> 7000 | D7: =Inputs!D13*Inputs!E13 -> 350 | E7: =Inputs!G13 -> 0.25 | F7: =D7*E7 -> 87.5 | G7: =Inputs!H13 -> 250 | H7: =ROUND(Inputs!D13*Inputs!E13*Inputs!C26*Inputs!G13*Inputs!H13,0) -> 0 | I7: =ROUND(Inputs!D13*Inputs!E13*Inputs!D26*Inputs!G13*Inputs!H13,0) -> 0 | J7: =ROUND(Inputs!D13*Inputs!E13*Inputs!E26*Inputs!G13*Inputs!H13,0) -> 4400 | K7: =ROUND(Inputs!D13*Inputs!E13*Inputs!F26*Inputs!G13*Inputs!H13,0) -> 17600
A8: =Inputs!B14 -> Assuta Pilot | B8: Accounting+Payments | C8: =Inputs!D14 -> 400 | D8: =Inputs!D14*Inputs!E14 -> 20 | E8: =Inputs!G14 -> 0.25 | F8: =D8*E8 -> 5 | G8: =Inputs!H14 -> 250 | H8: =ROUND(Inputs!D14*Inputs!E14*Inputs!C27*Inputs!G14*Inputs!H14,0) -> 0 | I8: =ROUND(Inputs!D14*Inputs!E14*Inputs!D27*Inputs!G14*Inputs!H14,0) -> 0 | J8: =ROUND(Inputs!D14*Inputs!E14*Inputs!E27*Inputs!G14*Inputs!H14,0) -> 625 | K8: =ROUND(Inputs!D14*Inputs!E14*Inputs!F27*Inputs!G14*Inputs!H14,0) -> 1250
A9: =Inputs!B15 -> Yango Deli | B9: Accounting | C9: =Inputs!D15 -> 2000 | D9: =Inputs!D15*Inputs!E15 -> 200 | E9: =Inputs!G15 -> 0.25 | F9: =D9*E9 -> 50 | G9: =Inputs!H15 -> 150 | H9: =ROUND(Inputs!D15*Inputs!E15*Inputs!C28*Inputs!G15*Inputs!H15,0) -> 0 | I9: =ROUND(Inputs!D15*Inputs!E15*Inputs!D28*Inputs!G15*Inputs!H15,0) -> 0 | J9: =ROUND(Inputs!D15*Inputs!E15*Inputs!E28*Inputs!G15*Inputs!H15,0) -> 2250 | K9: =ROUND(Inputs!D15*Inputs!E15*Inputs!F28*Inputs!G15*Inputs!H15,0) -> 7500
A10: =Inputs!B16 -> Wolt expand (existing) | B10: Accounting | C10: =Inputs!D16 -> 10000 | D10: =Inputs!D16*Inputs!E16 -> 1000 | E10: =Inputs!G16 -> 0.25 | F10: =D10*E10 -> 250 | G10: =Inputs!H16 -> 150 | H10: =ROUND(Inputs!D16*Inputs!E16*Inputs!C29*Inputs!G16*Inputs!H16,0) -> 5000 | I10: =ROUND(Inputs!D16*Inputs!E16*Inputs!D29*Inputs!G16*Inputs!H16,0) -> 7500 | J10: =ROUND(Inputs!D16*Inputs!E16*Inputs!E29*Inputs!G16*Inputs!H16,0) -> 11250 | K10: =ROUND(Inputs!D16*Inputs!E16*Inputs!F29*Inputs!G16*Inputs!H16,0) -> 15000
A11: =Inputs!B17 -> Wolt Merchants | B11: Accounting+Promoter | C11: =Inputs!D17 -> 4000 | D11: =Inputs!D17*Inputs!E17 -> 200 | E11: =Inputs!G17 -> 0.25 | F11: =D11*E11 -> 50 | G11: =Inputs!H17 -> 150 | H11: =ROUND(Inputs!D17*Inputs!E17*Inputs!C30*Inputs!G17*Inputs!H17,0) -> 0 | I11: =ROUND(Inputs!D17*Inputs!E17*Inputs!D30*Inputs!G17*Inputs!H17,0) -> 0 | J11: =ROUND(Inputs!D17*Inputs!E17*Inputs!E30*Inputs!G17*Inputs!H17,0) -> 2250 | K11: =ROUND(Inputs!D17*Inputs!E17*Inputs!F30*Inputs!G17*Inputs!H17,0) -> 7500
A12: =Inputs!B18 -> Wix Upsell | B12: Accounting | C12: =Inputs!D18 -> 20000 | D12: =Inputs!D18*Inputs!E18 -> 600 | E12: =Inputs!G18 -> 0.25 | F12: =D12*E12 -> 150 | G12: =Inputs!H18 -> 150 | H12: =ROUND(Inputs!D18*Inputs!E18*Inputs!C31*Inputs!G18*Inputs!H18,0) -> 0 | I12: =ROUND(Inputs!D18*Inputs!E18*Inputs!D31*Inputs!G18*Inputs!H18,0) -> 1500 | J12: =ROUND(Inputs!D18*Inputs!E18*Inputs!E31*Inputs!G18*Inputs!H18,0) -> 4500 | K12: =ROUND(Inputs!D18*Inputs!E18*Inputs!F31*Inputs!G18*Inputs!H18,0) -> 7500
A13: =Inputs!B19 -> Isracard/Cal | B13: Accounting+Promoter | C13: =Inputs!D19 -> 50000 | D13: =Inputs!D19*Inputs!E19 -> 0 | E13: =Inputs!G19 -> 0.2 | F13: =D13*E13 -> 0 | G13: =Inputs!H19 -> 175 | H13: =ROUND(Inputs!D19*Inputs!E19*Inputs!C32*Inputs!G19*Inputs!H19,0) -> 0 | I13: =ROUND(Inputs!D19*Inputs!E19*Inputs!D32*Inputs!G19*Inputs!H19,0) -> 0 | J13: =ROUND(Inputs!D19*Inputs!E19*Inputs!E32*Inputs!G19*Inputs!H19,0) -> 0 | K13: =ROUND(Inputs!D19*Inputs!E19*Inputs!F32*Inputs!G19*Inputs!H19,0) -> 0
A14: TOTAL MRR | H14: =SUM(H5:H13) -> 5000 | I14: =SUM(I5:I13) -> 13600 | J14: =SUM(J5:J13) -> 46975 | K14: =SUM(K5:K13) -> 102100
A15: TARGET | H15: 100000 | I15: 100000 | J15: 100000 | K15: 100000
A16: GAP TO TARGET | H16: =H15-H14 -> 95000 | I16: =I15-I14 -> 86400 | J16: =J15-J14 -> 53025 | K16: =K15-K14 -> -2100

Sheet Upside (140K+)
A1: TABLE: Monthly Revenue Forecast — Upside (Ceiling)
A2: Same formula structure as Conservative. Uses Upside exposure + Upside ramp from Inputs sheet.
A4: Partner | B4: Product | C4: Ecosystem | D4: Exposed (M4) | E4: Activation | F4: Active (M4) | G4: ARPU | H4: Month 1 | I4: Month 2 | J4: Month 3 | K4: Month 4
A5: =Inputs!B11 -> 10bis | B5: Accounting | C5: =Inputs!D11 -> 6000 | D5: =Inputs!D11*Inputs!F11 -> 1800 | E5: =Inputs!G11 -> 0.25 | F5: =D5*E5 -> 450 | G5: =Inputs!H11 -> 150 | H5: =ROUND(Inputs!D11*Inputs!F11*Inputs!G24*Inputs!G11*Inputs!H11,0) -> 0 | I5: =ROUND(Inputs!D11*Inputs!F11*Inputs!H24*Inputs!G11*Inputs!H11,0) -> 5000 | J5: =ROUND(Inputs!D11*Inputs!F11*Inputs!I24*Inputs!G11*Inputs!H11,0) -> 20000 | K5: =ROUND(Inputs!D11*Inputs!F11*Inputs!J24*Inputs!G11*Inputs!H11,0) -> 40000
A6: =Inputs!B12 -> Plannie | B6: Payments+Accounting | C6: =Inputs!D12 -> 3000 | D6: =Inputs!D12*Inputs!F12 -> 600 | E6: =Inputs!G12 -> 0.2 | F6: =D6*E6 -> 120 | G6: =Inputs!H12 -> 200 | H6: =ROUND(Inputs!D12*Inputs!F12*Inputs!G25*Inputs!G12*Inputs!H12,0) -> 0 | I6: =ROUND(Inputs!D12*Inputs!F12*Inputs!H25*Inputs!G12*Inputs!H12,0) -> 2400 | J6: =ROUND(Inputs!D12*Inputs!F12*Inputs!I25*Inputs!G12*Inputs!H12,0) -> 7200 | K6: =ROUND(Inputs!D12*Inputs!F12*Inputs!J25*Inputs!G12*Inputs!H12,0) -> 18000
A7: =Inputs!B13 -> Arbox | B7: Accounting+Promoter | C7: =Inputs!D13 -> 7000 | D7: =Inputs!D13*Inputs!F13 -> 700 | E7: =Inputs!G13 -> 0.25 | F7: =D7*E7 -> 175 | G7: =Inputs!H13 -> 250 | H7: =ROUND(Inputs!D13*Inputs!F13*Inputs!G26*Inputs!G13*Inputs!H13,0) -> 0 | I7: =ROUND(Inputs!D13*Inputs!F13*Inputs!H26*Inputs!G13*Inputs!H13,0) -> 0 | J7: =ROUND(Inputs!D13*Inputs!F13*Inputs!I26*Inputs!G13*Inputs!H13,0) -> 7500 | K7: =ROUND(Inputs!D13*Inputs!F13*Inputs!J26*Inputs!G13*Inputs!H13,0) -> 25000
A8: =Inputs!B14 -> Assuta Pilot | B8: Accounting+Payments | C8: =Inputs!D14 -> 400 | D8: =Inputs!D14*Inputs!F14 -> 50 | E8: =Inputs!G14 -> 0.25 | F8: =D8*E8 -> 12.5 | G8: =Inputs!H14 -> 250 | H8: =ROUND(Inputs!D14*Inputs!F14*Inputs!G27*Inputs!G14*Inputs!H14,0) -> 0 | I8: =ROUND(Inputs!D14*Inputs!F14*Inputs!H27*Inputs!G14*Inputs!H14,0) -> 0 | J8: =ROUND(Inputs!D14*Inputs!F14*Inputs!I27*Inputs!G14*Inputs!H14,0) -> 1500 | K8: =ROUND(Inputs!D14*Inputs!F14*Inputs!J27*Inputs!G14*Inputs!H14,0) -> 3000
A9: =Inputs!B15 -> Yango Deli | B9: Accounting | C9: =Inputs!D15 -> 2000 | D9: =Inputs!D15*Inputs!F15 -> 400 | E9: =Inputs!G15 -> 0.25 | F9: =D9*E9 -> 100 | G9: =Inputs!H15 -> 150 | H9: =ROUND(Inputs!D15*Inputs!F15*Inputs!G28*Inputs!G15*Inputs!H15,0) -> 0 | I9: =ROUND(Inputs!D15*Inputs!F15*Inputs!H28*Inputs!G15*Inputs!H15,0) -> 0 | J9: =ROUND(Inputs!D15*Inputs!F15*Inputs!I28*Inputs!G15*Inputs!H15,0) -> 3000 | K9: =ROUND(Inputs!D15*Inputs!F15*Inputs!J28*Inputs!G15*Inputs!H15,0) -> 10000
A10: =Inputs!B16 -> Wolt expand (existing) | B10: Accounting | C10: =Inputs!D16 -> 10000 | D10: =Inputs!D16*Inputs!F16 -> 1500 | E10: =Inputs!G16 -> 0.25 | F10: =D10*E10 -> 375 | G10: =Inputs!H16 -> 150 | H10: =ROUND(Inputs!D16*Inputs!F16*Inputs!G29*Inputs!G16*Inputs!H16,0) -> 6000 | I10: =ROUND(Inputs!D16*Inputs!F16*Inputs!H29*Inputs!G16*Inputs!H16,0) -> 9000 | J10: =ROUND(Inputs!D16*Inputs!F16*Inputs!I29*Inputs!G16*Inputs!H16,0) -> 14000 | K10: =ROUND(Inputs!D16*Inputs!F16*Inputs!J29*Inputs!G16*Inputs!H16,0) -> 18000
A11: =Inputs!B17 -> Wolt Merchants | B11: Accounting+Promoter | C11: =Inputs!D17 -> 4000 | D11: =Inputs!D17*Inputs!F17 -> 400 | E11: =Inputs!G17 -> 0.25 | F11: =D11*E11 -> 100 | G11: =Inputs!H17 -> 150 | H11: =ROUND(Inputs!D17*Inputs!F17*Inputs!G30*Inputs!G17*Inputs!H17,0) -> 0 | I11: =ROUND(Inputs!D17*Inputs!F17*Inputs!H30*Inputs!G17*Inputs!H17,0) -> 0 | J11: =ROUND(Inputs!D17*Inputs!F17*Inputs!I30*Inputs!G17*Inputs!H17,0) -> 3500 | K11: =ROUND(Inputs!D17*Inputs!F17*Inputs!J30*Inputs!G17*Inputs!H17,0) -> 10000
A12: =Inputs!B18 -> Wix Upsell | B12: Accounting | C12: =Inputs!D18 -> 20000 | D12: =Inputs!D18*Inputs!F18 -> 1000 | E12: =Inputs!G18 -> 0.25 | F12: =D12*E12 -> 250 | G12: =Inputs!H18 -> 150 | H12: =ROUND(Inputs!D18*Inputs!F18*Inputs!G31*Inputs!G18*Inputs!H18,0) -> 0 | I12: =ROUND(Inputs!D18*Inputs!F18*Inputs!H31*Inputs!G18*Inputs!H18,0) -> 2000 | J12: =ROUND(Inputs!D18*Inputs!F18*Inputs!I31*Inputs!G18*Inputs!H18,0) -> 6000 | K12: =ROUND(Inputs!D18*Inputs!F18*Inputs!J31*Inputs!G18*Inputs!H18,0) -> 12000
A13: =Inputs!B19 -> Isracard/Cal | B13: Accounting+Promoter | C13: =Inputs!D19 -> 50000 | D13: =Inputs!D19*Inputs!F19 -> 500 | E13: =Inputs!G19 -> 0.2 | F13: =D13*E13 -> 100 | G13: =Inputs!H19 -> 175 | H13: =ROUND(Inputs!D19*Inputs!F19*Inputs!G32*Inputs!G19*Inputs!H19,0) -> 0 | I13: =ROUND(Inputs!D19*Inputs!F19*Inputs!H32*Inputs!G19*Inputs!H19,0) -> 0 | J13: =ROUND(Inputs!D19*Inputs!F19*Inputs!I32*Inputs!G19*Inputs!H19,0) -> 0 | K13: =ROUND(Inputs!D19*Inputs!F19*Inputs!J32*Inputs!G19*Inputs!H19,0) -> 5000
A14: TOTAL MRR | H14: =SUM(H5:H13) -> 6000 | I14: =SUM(I5:I13) -> 18400 | J14: =SUM(J5:J13) -> 62700 | K14: =SUM(K5:K13) -> 141000
A15: TARGET | H15: 100000 | I15: 100000 | J15: 100000 | K15: 100000
A16: SURPLUS ABOVE TARGET | H16: =H14-H15 -> -94000 | I16: =I14-I15 -> -81600 | J16: =J14-J15 -> -37300 | K16: =K14-K15 -> 41000

Sheet Scenario Comparison
A1: Scenario Comparison
B3: Month 1 | C3: Month 2 | D3: Month 3 | E3: Month 4
A4: Conservative | B4: ='Conservative (100K)'!H14 -> 5000 | C4: ='Conservative (100K)'!I14 -> 13600 | D4: ='Conservative (100K)'!J14 -> 46975 | E4: ='Conservative (100K)'!K14 -> 102100
A5: Upside | B5: ='Upside (140K+)'!H14 -> 6000 | C5: ='Upside (140K+)'!I14 -> 18400 | D5: ='Upside (140K+)'!J14 -> 62700 | E5: ='Upside (140K+)'!K14 -> 141000
A6: TARGET | B6: 100000 | C6: 100000 | D6: 100000 | E6: 100000
A8: What changes between scenarios:
A9: 1. Exposure: Conservative 15% of ecosystem, Upside 30% — depends on partner rollout speed
A10: 2. Deal closure: Conservative 60% assumption, Upside 80%
A11: 3. Promoter: Conservative = minimal, Upside = active in Arbox (higher blended ARPU)
A12: 4. Isracard/Cal: Conservative = not ready by M4, Upside = joins with 5,000 ILS MRR
A13: 5. Assuta: Conservative = 1 physician group (20 doctors), Upside = 2 groups + HMC (50 doctors)
A14: 6. Inbound base: Conservative = Wolt expand + Wix only. Upside adds Isracard + Wolt Merchants at scale

Sheet Global Platforms (Future)
A1: Global Platform Ecosystem — Documented Opportunity, NOT in Committed Forecast
A2: IMPORTANT: Figures below are GLOBAL user/site counts, not Israel-specific. Israeli subset is unknown and unvalidated. This segment is excluded from the Conservative (102,100) and Upside (141,000) MRR totals until validated.
A4: Why this segment matters
A5: Elementor is an Israeli company (Ramat Gan, CEO Yoni Luksenberg) with a global product used by millions of Israeli and international site owners. Like Wix, it has no native Israeli invoicing layer for its Israeli merchant base. Same logic as the validated Wix opportunity, at larger scale but unconfirmed local penetration.
A7: Platform | B7: Global Scale | C7: Native Payments? | D7: Relevant PayMe Product | E7: Source | F7: Readiness Tier
A8: Elementor | B8: 21M+ websites since 2016 (13% of the web); 2-3M on paid Elementor Pro; $75.9M annual revenue; 365 employees | C8: No. Relies entirely on 3rd-party plugins (Stripe is official Verified Partner) | D8: Accounting (Israeli invoicing for IL merchants) — NOT competing with Stripe on global payments | E8: Colorlib Elementor Statistics 2026; RocketReach | F8: Problem, Low Awareness
A9: BuddyBoss | B9: 50,000+ customers worldwide; 27,000 active Platform/Theme installs; clients include Stanford, MIT, Yale | C9: No. Relies on WooCommerce + Stripe/PayPal integrations | D9: Accounting for Israeli course/community creators | E9: BuddyBoss.com; Awesome Motive acquisition press release (2025); Cybernews | F9: Problem, Low Awareness
A10: LearnDash | B10: ~55,600 live sites currently (162,600+ historically); one support agency alone serves 6,000+ customers | C10: No. Relies on Stripe Connect, PayPal, Razorpay | D10: Accounting for Israeli course creators | E10: BuiltWith Trends; WooNinjas LearnDash Support report | F10: Problem, Low Awareness
A12: Recommended framing: NOT 'Ready to Partner' — global platforms need Education & Enablement before Outbound (per Partner Prioritization Framework). Do not add to MRR forecast until Israeli user-base size is confirmed via direct research (e.g., LinkedIn Sales Navigator filtering by country, or direct outreach to gauge interest).
A14: Next step to validate before including in forecast:
A15: 1. Estimate Israeli user base: search LinkedIn / BuiltWith filtered by Israel domains using Elementor/LearnDash/BuddyBoss
A16: 2. Confirm the pain: survey or interview 5-10 Israeli users of each platform about their current invoicing/payments setup
A17: 3. Identify decision maker: for Elementor specifically (Israeli company), map BD/Partnerships contact
A18: 4. Only then: assign exposure %, activation rate, and ARPU assumptions consistent with the Inputs sheet methodology
